LICENSE
MANIFEST.in
README.md
setup.cfg
setup.py
tilejet_util.egg-info/PKG-INFO
tilejet_util.egg-info/SOURCES.txt
tilejet_util.egg-info/dependency_links.txt
tilejet_util.egg-info/top_level.txt
tilejetutil/__init__.py
tilejetutil/base.py
tilejetutil/nav.py
tilejetutil/tilefactory.py
tilejetutil/tilemath.py
tilejetutil/tileregex.py